{
  "count": 548,
  "next": "https://goriva.si/api/v1/search/?format=json&franchise=&name=&o=&page=16&position=&radius=",
  "previous": "https://goriva.si/api/v1/search/?format=json&franchise=&name=&o=&page=14&position=&radius=",
  "results": [
    {
      "pk": 2219,
      "franchise": 1,
      "name": "PETROL DOBRNA",
      "address": "PRISTOVA 21",
      "lat": 46.32717529,
      "lng": 15.22104794,
      "prices": {
        "95": 1.717,
        "dizel": 1.862,
        "98": null,
        "100": null,
        "dizel-premium": null,
        "avtoplin-lpg": null,
        "KOEL": 1.374
      },
      "distance": null,
      "direction": "",
      "open_hours": "vsak delavnik 07:00-19:00\r\nsobote 07:00-17:00\r\nnedelje in prazniki 08:30-12:00",
      "zip_code": "3204"
    },
    {
      "pk": 1964,
      "franchise": 1,
      "name": "PETROL DOLNJI LAKOŠ",
      "address": "GLAVNA ULICA 3",
      "lat": 46.55372124,
      "lng": 16.44233518,
      "prices": {
        "95": 1.717,
        "dizel": 1.862,
        "98": null,
        "100": null,
        "dizel-premium": null,
        "avtoplin-lpg": null,
        "KOEL": 1.374
      },
      "distance": null,
      "direction": "",
      "open_hours": "vsak delavnik 06:00-20:00\r\nsobote 06:00-20:00\r\nnedelje in prazniki 08:00-20:00",
      "zip_code": "9220"
    },
    {
      "pk": 2220,
      "franchise": 1,
      "name": "PETROL KOČEVJE - LJUBLJANSKA ZAHOD",
      "address": "LJUBLJANSKA CESTA 69A",
      "lat": 45.64870304,
      "lng": 14.85374303,
      "prices": {
        "95": 1.717,
        "dizel": 1.862,
        "98": null,
        "100": 1.927,
        "dizel-premium": 2.2,
        "avtoplin-lpg": 1.057,
        "KOEL": 1.374
      },
      "distance": null,
      "direction": "",
      "open_hours": "vsak delavnik 06:00-22:00\r\nsobote 06:00-22:00\r\nnedelje in prazniki 06:00-22:00",
      "zip_code": "1330"
    },
    {
      "pk": 1965,
      "franchise": 1,
      "name": "PETROL RADENCI",
      "address": "RADGONSKA CESTA 14",
      "lat": 46.64504675,
      "lng": 16.03435514,
      "prices": {
        "95": 1.717,
        "dizel": 1.862,
        "98": null,
        "100": null,
        "dizel-premium": null,
        "avtoplin-lpg": null,
        "KOEL": 1.374
      },
      "distance": null,
      "direction": "",
      "open_hours": "vsak delavnik 06:00-20:00\r\nsobote 06:00-20:00\r\nnedelje in prazniki 08:30-12:00",
      "zip_code": "9252"
    },
    {
      "pk": 2221,
      "franchise": 1,
      "name": "PETROL ŽLEBIČ",
      "address": "BREŽE 1B",
      "lat": 45.76220176,
      "lng": 14.70303872,
      "prices": {
        "95": 1.717,
        "dizel": 1.862,
        "98": null,
        "100": 1.927,
        "dizel-premium": null,
        "avtoplin-lpg": null,
        "KOEL": 1.374
      },
      "distance": null,
      "direction": "",
      "open_hours": "vsak delavnik 05:00-22:00\r\nsobote 06:00-22:00\r\nnedelje in prazniki 06:00-22:00",
      "zip_code": "1310"
    },
    {
      "pk": 1966,
      "franchise": 1,
      "name": "PETROL BELTINCI",
      "address": "PANONSKA ULICA 2B",
      "lat": 46.6116377,
      "lng": 16.22745614,
      "prices": {
        "95": 1.717,
        "dizel": 1.862,
        "98": null,
        "100": 1.927,
        "dizel-premium": null,
        "avtoplin-lpg": null,
        "KOEL": 1.374
      },
      "distance": null,
      "direction": "",
      "open_hours": "vsak delavnik 06:00-22:00\r\nsobote 06:00-22:00\r\nnedelje in prazniki 07:00-21:00",
      "zip_code": "9231"
    },
    {
      "pk": 2222,
      "franchise": 1,
      "name": "PETROL KOČEVJE - LJUBLJANSKA VZHOD",
      "address": "LJUBLJANSKA CESTA 44",
      "lat": 45.64954924,
      "lng": 14.85397187,
      "prices": {
        "95": 1.717,
        "dizel": 1.862,
        "98": null,
        "100": 1.927,
        "dizel-premium": null,
        "avtoplin-lpg": null,
        "KOEL": 1.374
      },
      "distance": null,
      "direction": "",
      "open_hours": "vsak delavnik 05:00-20:00\r\nsobote 12:30-15:00",
      "zip_code": "1330"
    },
    {
      "pk": 1967,
      "franchise": 1,
      "name": "PETROL KRIŽEVCI",
      "address": "KLJUČAROVCI PRI LJUTOMERU 83",
      "lat": 46.55783512,
      "lng": 16.14313338,
      "prices": {
        "95": 1.717,
        "dizel": 1.862,
        "98": null,
        "100": null,
        "dizel-premium": null,
        "avtoplin-lpg": null,
        "KOEL": 1.374
      },
      "distance": null,
      "direction": "",
      "open_hours": "vsak delavnik 06:00-20:00\r\nsobote 07:00-20:00\r\nnedelje in prazniki 08:00-11:30",
      "zip_code": "9242"
    },
    {
      "pk": 2223,
      "franchise": 1,
      "name": "PETROL PETRINA",
      "address": "PETRINA 10",
      "lat": 45.46509102,
      "lng": 14.8550985,
      "prices": {
        "95": 1.717,
        "dizel": 1.862,
        "98": null,
        "100": null,
        "dizel-premium": null,
        "avtoplin-lpg": null,
        "KOEL": 1.374
      },
      "distance": null,
      "direction": "",
      "open_hours": "vsak delavnik 12:30-18:00\r\nsobote 11:00-13:00",
      "zip_code": "1336"
    },
    {
      "pk": 1968,
      "franchise": 1,
      "name": "PETROL DOBROVNIK",
      "address": "DOBROVNIK 4A",
      "lat": 46.65099893,
      "lng": 16.35338368,
      "prices": {
        "95": 1.717,
        "dizel": 1.862,
        "98": null,
        "100": null,
        "dizel-premium": null,
        "avtoplin-lpg": null,
        "KOEL": 1.374
      },
      "distance": null,
      "direction": "",
      "open_hours": "vsak delavnik 07:00-20:00\r\nsobote 07:00-20:00\r\nnedelje in prazniki 08:30-12:00",
      "zip_code": "9223"
    },
    {
      "pk": 2224,
      "franchise": 1,
      "name": "PETROL LOŠKI POTOK",
      "address": "MALI LOG 2B",
      "lat": 45.717099,
      "lng": 14.58622,
      "prices": {
        "95": 1.717,
        "dizel": 1.862,
        "98": null,
        "100": null,
        "dizel-premium": null,
        "avtoplin-lpg": null,
        "KOEL": 1.374
      },
      "distance": null,
      "direction": "",
      "open_hours": "vsak delavnik 12:00-16:00\r\nsobote 08:00-12:00",
      "zip_code": "1318"
    },
    {
      "pk": 1969,
      "franchise": 1,
      "name": "PETROL ODRANCI",
      "address": "NASELJE GREDICE 1A",
      "lat": 46.58197141,
      "lng": 16.28224598,
      "prices": {
        "95": 1.717,
        "dizel": 1.862,
        "98": null,
        "100": 1.927,
        "dizel-premium": null,
        "avtoplin-lpg": null,
        "KOEL": 1.374
      },
      "distance": null,
      "direction": "Maribor -> Madžarska",
      "open_hours": "vsak delavnik 06:00-21:00\r\nsobote 06:00-21:00\r\nnedelje in prazniki 08:00-19:00",
      "zip_code": "9233"
    },
    {
      "pk": 2225,
      "franchise": 1,
      "name": "PETROL NOVO MESTO - TOPLIŠKA",
      "address": "TOPLIŠKA CESTA 9",
      "lat": 45.79863637,
      "lng": 15.15095997,
      "prices": {
        "95": 1.717,
        "dizel": 1.862,
        "98": null,
        "100": 1.927,
        "dizel-premium": null,
        "avtoplin-lpg": null,
        "KOEL": 1.374
      },
      "distance": null,
      "direction": "",
      "open_hours": "vsak delavnik 06:00-22:00\r\nsobote 06:00-22:00\r\nnedelje in prazniki 07:30-21:00",
      "zip_code": "8000"
    },
    {
      "pk": 1970,
      "franchise": 1,
      "name": "PETROL GORNJA RADGONA - MELE",
      "address": "LJUTOMERSKA CESTA 36",
      "lat": 46.66198841,
      "lng": 16.01446177,
      "prices": {
        "95": 1.717,
        "dizel": 1.862,
        "98": null,
        "100": 1.927,
        "dizel-premium": null,
        "avtoplin-lpg": 1.057,
        "KOEL": 1.374
      },
      "distance": null,
      "direction": "",
      "open_hours": "vsak delavnik 06:00-21:00\r\nsobote 07:00-21:00\r\nnedelje in prazniki 07:00-21:00",
      "zip_code": "9250"
    },
    {
      "pk": 1971,
      "franchise": 1,
      "name": "PETROL MARTJANCI",
      "address": "MARTJANCI 83B",
      "lat": 46.68760198,
      "lng": 16.19649434,
      "prices": {
        "95": 1.717,
        "dizel": 1.862,
        "98": null,
        "100": 1.927,
        "dizel-premium": null,
        "avtoplin-lpg": null,
        "KOEL": null
      },
      "distance": null,
      "direction": "",
      "open_hours": "vsak delavnik 06:00-21:00\r\nsobote 06:00-21:00\r\nnedelje in prazniki 08:00-19:30",
      "zip_code": "9221"
    },
    {
      "pk": 2227,
      "franchise": 1,
      "name": "PETROL NOVO MESTO - BRŠLJIN",
      "address": "LJUBLJANSKA CESTA 28A",
      "lat": 45.81628712,
      "lng": 15.1547285,
      "prices": {
        "95": 1.717,
        "dizel": 1.862,
        "98": null,
        "100": 1.927,
        "dizel-premium": null,
        "avtoplin-lpg": 1.057,
        "KOEL": null
      },
      "distance": null,
      "direction": "",
      "open_hours": "vsak delavnik 06:00-22:00\r\nsobote 06:00-22:00\r\nnedelje in prazniki 07:00-22:00",
      "zip_code": "8000"
    },
    {
      "pk": 1972,
      "franchise": 1,
      "name": "PETROL MURSKA SOBOTA - TIŠINSKA JUG",
      "address": "TIŠINSKA ULICA 29D",
      "lat": 46.651421,
      "lng": 16.14565,
      "prices": {
        "95": 1.717,
        "dizel": 1.862,
        "98": null,
        "100": 1.927,
        "dizel-premium": null,
        "avtoplin-lpg": 1.057,
        "KOEL": 1.374
      },
      "distance": null,
      "direction": "",
      "open_hours": "vsak delavnik 06:00-22:00\r\nsobote 06:00-22:00\r\nnedelje in prazniki 07:00-21:00",
      "zip_code": "9000"
    },
    {
      "pk": 2228,
      "franchise": 1,
      "name": "PETROL NOVO MESTO - ŽABJA VAS",
      "address": "BELOKRANJSKA CESTA 3",
      "lat": 45.797682,
      "lng": 15.181242,
      "prices": {
        "95": 1.717,
        "dizel": 1.862,
        "98": null,
        "100": 1.927,
        "dizel-premium": null,
        "avtoplin-lpg": 1.057,
        "KOEL": 1.374
      },
      "distance": null,
      "direction": "",
      "open_hours": "NON-STOP",
      "zip_code": "8000"
    },
    {
      "pk": 1973,
      "franchise": 1,
      "name": "PETROL GODOVIČ",
      "address": "GODOVIČ 2B",
      "lat": 45.95665729,
      "lng": 14.09433635,
      "prices": {
        "95": 1.717,
        "dizel": 1.862,
        "98": null,
        "100": null,
        "dizel-premium": null,
        "avtoplin-lpg": null,
        "KOEL": 1.374
      },
      "distance": null,
      "direction": "",
      "open_hours": "vsak delavnik 07:00-19:00\r\nsobote 07:00-19:00",
      "zip_code": "5275"
    },
    {
      "pk": 1974,
      "franchise": 1,
      "name": "PETROL CANKOVA",
      "address": "CANKOVA 35",
      "lat": 46.71906544,
      "lng": 16.02095244,
      "prices": {
        "95": 1.717,
        "dizel": 1.862,
        "98": null,
        "100": null,
        "dizel-premium": null,
        "avtoplin-lpg": null,
        "KOEL": 1.374
      },
      "distance": null,
      "direction": "",
      "open_hours": "vsak delavnik 07:00-18:00\r\nsobote 07:00-13:00\r\nnedelje in prazniki 08:00-12:00",
      "zip_code": "9261"
    },
    {
      "pk": 1975,
      "franchise": 1,
      "name": "PETROL KUZMA",
      "address": "KUZMA 26B",
      "lat": 46.83371949,
      "lng": 16.08249735,
      "prices": {
        "95": 1.717,
        "dizel": 1.862,
        "98": null,
        "100": null,
        "dizel-premium": null,
        "avtoplin-lpg": null,
        "KOEL": 1.374
      },
      "distance": null,
      "direction": "",
      "open_hours": "vsak delavnik 07:30-18:00\r\nsobote 07:30-13:00\r\nnedelje08:00-12:00",
      "zip_code": "9263"
    },
    {
      "pk": 2233,
      "franchise": 1,
      "name": "PETROL MENGEŠ - KAMNIŠKA",
      "address": "KAMNIŠKA CESTA 60",
      "lat": 46.172911,
      "lng": 14.577254,
      "prices": {
        "95": 1.717,
        "dizel": 1.862,
        "98": null,
        "100": 1.927,
        "dizel-premium": null,
        "avtoplin-lpg": 1.057,
        "KOEL": null
      },
      "distance": null,
      "direction": "Ljubljana -> Maribor",
      "open_hours": "vsak delavnik 05:00-22:00\r\nsobote 06:00-22:00\r\nnedelje in prazniki 07:00-21:00",
      "zip_code": "1234"
    },
    {
      "pk": 2234,
      "franchise": 4,
      "name": "BS MOL TEZNO",
      "address": "Ptujska cesta 56",
      "lat": 46.537696,
      "lng": 15.655975,
      "prices": {
        "95": 1.717,
        "dizel": 1.862,
        "98": null,
        "100": 1.942,
        "dizel-premium": 1.999,
        "avtoplin-lpg": 1.057,
        "KOEL": null
      },
      "distance": null,
      "direction": "",
      "open_hours": "Odpiralni čas:\r\nPonedeljek - petek:            05:00 - 22:00\r\nSobota:                                06:00 - 22:00\r\nNedelja:                               06:00 - 22:00\r\nPrazniki:                               06:00 - 22:00",
      "zip_code": "2000"
    },
    {
      "pk": 1979,
      "franchise": 1,
      "name": "PETROL VUČJA VAS",
      "address": "BUČEČOVCI 4B",
      "lat": 46.591207,
      "lng": 16.10787,
      "prices": {
        "95": 1.717,
        "dizel": 1.862,
        "98": null,
        "100": 1.927,
        "dizel-premium": null,
        "avtoplin-lpg": null,
        "KOEL": 1.374
      },
      "distance": null,
      "direction": "Maribor -> Pince",
      "open_hours": "vsak delavnik 06:00-22:00\r\nsobote 06:00-22:00\r\nnedelje in prazniki 07:00-19:00",
      "zip_code": "9242"
    },
    {
      "pk": 2235,
      "franchise": 4,
      "name": "BS MOL KRANJ",
      "address": "Ulica Boštjana Hladnika 4",
      "lat": 46.230565,
      "lng": 14.369373,
      "prices": {
        "95": 1.717,
        "dizel": 1.862,
        "98": null,
        "100": 1.942,
        "dizel-premium": 1.999,
        "avtoplin-lpg": 1.057,
        "KOEL": null
      },
      "distance": null,
      "direction": "",
      "open_hours": "PON - SOB 06:00 - 22:00\r\nNEDELJA IN PRAZNIKI 08:00 - 20:00",
      "zip_code": "4000"
    }
  ],
  "position": null
}
