{
  "count": 548,
  "next": "https://goriva.si/api/v1/search/?format=json&franchise=&name=&o=&page=3&position=&radius=",
  "previous": "https://goriva.si/api/v1/search/?format=json&franchise=&name=&o=&position=&radius=",
  "results": [
    {
      "pk": 808,
      "franchise": 2,
      "name": "OMV KOZINA",
      "address": "Mestni trg 7",
      "lat": 45.60807,
      "lng": 13.93501,
      "prices": {
        "95": 1.354,
        "dizel": 1.683,
        "98": null,
        "100": 1.695,
        "dizel-premium": null,
        "avtoplin-lpg": null,
        "KOEL": null
      },
      "distance": null,
      "direction": "",
      "open_hours": "Pon-Ned 00:00-24:00",
      "zip_code": "6240"
    },
    {
      "pk": 809,
      "franchise": 2,
      "name": "OMV KRANJ",
      "address": "Cesta Staneta Žagarja 53c",
      "lat": 46.24277,
      "lng": 14.371453,
      "prices": {
        "95": 1.354,
        "dizel": 1.683,
        "98": null,
        "100": 1.695,
        "dizel-premium": null,
        "avtoplin-lpg": null,
        "KOEL": null
      },
      "distance": null,
      "direction": "",
      "open_hours": "Pon-Ned 06:00-22:00",
      "zip_code": "4000"
    },
    {
      "pk": 810,
      "franchise": 2,
      "name": "OMV KRŠKO",
      "address": "C.Krških žrtev 131a",
      "lat": 45.94429,
      "lng": 15.48733,
      "prices": {
        "95": 1.354,
        "dizel": 1.683,
        "98": null,
        "100": 1.695,
        "dizel-premium": 1.887,
        "avtoplin-lpg": null,
        "KOEL": 1.366
      },
      "distance": null,
      "direction": "",
      "open_hours": "Pon-Ned 00:00-24:00",
      "zip_code": "8270"
    },
    {
      "pk": 811,
      "franchise": 2,
      "name": "OMV KRVAVI POTOK",
      "address": "Krvavi potok 1",
      "lat": 45.61885,
      "lng": 13.910126,
      "prices": {
        "95": 1.354,
        "dizel": 1.683,
        "98": null,
        "100": null,
        "dizel-premium": null,
        "avtoplin-lpg": null,
        "KOEL": null
      },
      "distance": null,
      "direction": "Trst",
      "open_hours": "Okt-Maj: Pon-Sob 07:00-21:00, Ned/Praz. zaprto; Jun-Sep: Pon-Ned 06:00-22:00",
      "zip_code": "6240"
    },
    {
      "pk": 812,
      "franchise": 2,
      "name": "OMV LAZARET",
      "address": "Jadranska c. 1",
      "lat": 45.59283,
      "lng": 13.72411,
      "prices": {
        "95": 1.354,
        "dizel": 1.683,
        "98": null,
        "100": 1.695,
        "dizel-premium": 1.887,
        "avtoplin-lpg": null,
        "KOEL": null
      },
      "distance": null,
      "direction": "Koper",
      "open_hours": "Okt-Mar: Pon-Ned 07:00-20:00; Apr-Maj: Pon-Ned 07:00-21:00; Jun-Sep: Pon-Ned 07:00-22:00",
      "zip_code": "6280"
    },
    {
      "pk": 813,
      "franchise": 2,
      "name": "OMV LESCE",
      "address": "Hraška c. 17",
      "lat": 46.365369,
      "lng": 14.16032,
      "prices": {
        "95": 1.354,
        "dizel": 1.683,
        "98": null,
        "100": 1.695,
        "dizel-premium": null,
        "avtoplin-lpg": null,
        "KOEL": null
      },
      "distance": null,
      "direction": "",
      "open_hours": "Pon-Ned 06:00-22:00",
      "zip_code": "4248"
    },
    {
      "pk": 814,
      "franchise": 2,
      "name": "OMV LIPOVCI",
      "address": "Lipovci 243b",
      "lat": 46.625125,
      "lng": 16.214332,
      "prices": {
        "95": 1.354,
        "dizel": 1.683,
        "98": null,
        "100": 1.695,
        "dizel-premium": null,
        "avtoplin-lpg": null,
        "KOEL": 1.366
      },
      "distance": null,
      "direction": "",
      "open_hours": "Pon-Ned 05:00-22:00",
      "zip_code": "9231"
    },
    {
      "pk": 815,
      "franchise": 2,
      "name": "OMV LITIJA",
      "address": "Zasavska c. 1",
      "lat": 46.058713,
      "lng": 14.832858,
      "prices": {
        "95": 1.354,
        "dizel": 1.683,
        "98": null,
        "100": 1.695,
        "dizel-premium": 1.887,
        "avtoplin-lpg": null,
        "KOEL": 1.366
      },
      "distance": null,
      "direction": "",
      "open_hours": "Pon-Sob 05:00-22:00, Ned/Praz 07:00-22:00",
      "zip_code": "1270"
    },
    {
      "pk": 816,
      "franchise": 2,
      "name": "OMV LJUBLJANA LETALIŠKA",
      "address": "Letališka c. 33b",
      "lat": 46.062474,
      "lng": 14.570349,
      "prices": {
        "95": 1.354,
        "dizel": 1.683,
        "98": null,
        "100": 1.695,
        "dizel-premium": null,
        "avtoplin-lpg": null,
        "KOEL": null
      },
      "distance": null,
      "direction": "",
      "open_hours": "Pon-Pet 06:00-22:00, Sob 08:00-20:00, Ned/Praz. zaprto",
      "zip_code": "1000"
    },
    {
      "pk": 817,
      "franchise": 2,
      "name": "OMV LJUBLJANA LITIJSKA",
      "address": "Litijska c. 40",
      "lat": 46.047401,
      "lng": 14.546097,
      "prices": {
        "95": 1.354,
        "dizel": 1.683,
        "98": null,
        "100": 1.695,
        "dizel-premium": 1.887,
        "avtoplin-lpg": null,
        "KOEL": null
      },
      "distance": null,
      "direction": "",
      "open_hours": "Pon-Ned 06:00-22:00",
      "zip_code": "1000"
    },
    {
      "pk": 818,
      "franchise": 2,
      "name": "OMV LJUBLJANA ŠENTVID",
      "address": "Celovška c. 455",
      "lat": 46.09891,
      "lng": 14.460958,
      "prices": {
        "95": 1.354,
        "dizel": 1.683,
        "98": null,
        "100": 1.695,
        "dizel-premium": null,
        "avtoplin-lpg": null,
        "KOEL": null
      },
      "distance": null,
      "direction": "",
      "open_hours": "Pon-Ned 00:00-24:00",
      "zip_code": "1210"
    },
    {
      "pk": 819,
      "franchise": 2,
      "name": "OMV LJUBLJANA ZALOŠKA JUG",
      "address": "Zaloška 158",
      "lat": 46.05628,
      "lng": 14.562775,
      "prices": {
        "95": 1.354,
        "dizel": 1.683,
        "98": null,
        "100": 1.695,
        "dizel-premium": 1.887,
        "avtoplin-lpg": null,
        "KOEL": null
      },
      "distance": null,
      "direction": "",
      "open_hours": "Pon-Ned 06:00-22:00",
      "zip_code": "1000"
    },
    {
      "pk": 820,
      "franchise": 2,
      "name": "OMV LJUBLJANA ZALOŠKA SEVER",
      "address": "Zaloška 157",
      "lat": 46.056444,
      "lng": 14.55814,
      "prices": {
        "95": 1.354,
        "dizel": 1.683,
        "98": null,
        "100": 1.695,
        "dizel-premium": 1.887,
        "avtoplin-lpg": null,
        "KOEL": null
      },
      "distance": null,
      "direction": "",
      "open_hours": "Pon-Ned 06:00-22:00",
      "zip_code": "1000"
    },
    {
      "pk": 821,
      "franchise": 2,
      "name": "OMV LJUTOMER",
      "address": "Kolodvorska 7a",
      "lat": 46.5289,
      "lng": 16.19006,
      "prices": {
        "95": 1.354,
        "dizel": 1.683,
        "98": null,
        "100": 1.695,
        "dizel-premium": null,
        "avtoplin-lpg": null,
        "KOEL": 1.366
      },
      "distance": null,
      "direction": "",
      "open_hours": "Pon-Ned 06:00-22:00",
      "zip_code": "9240"
    },
    {
      "pk": 822,
      "franchise": 2,
      "name": "OMV LOKEV",
      "address": "Lokev 1a",
      "lat": 45.66133,
      "lng": 13.91942,
      "prices": {
        "95": 1.354,
        "dizel": 1.683,
        "98": null,
        "100": 1.695,
        "dizel-premium": null,
        "avtoplin-lpg": null,
        "KOEL": null
      },
      "distance": null,
      "direction": "",
      "open_hours": "Okt-Mar: Pon-Ned 07:00-19:00; Apr-Sep: Pon-Ned 07:00-20:00",
      "zip_code": "6219"
    },
    {
      "pk": 824,
      "franchise": 2,
      "name": "OMV LUCIJA POMOL",
      "address": "Seča 188",
      "lat": 45.50526,
      "lng": 13.59658,
      "prices": {
        "95": 1.354,
        "dizel": 1.683,
        "98": null,
        "100": null,
        "dizel-premium": null,
        "avtoplin-lpg": null,
        "KOEL": null
      },
      "distance": null,
      "direction": "",
      "open_hours": "Okt-Maj: na klic ; Jun-Sep: Pon-Ned 09:00-19:00 (zaprto od 13:00-14:00)",
      "zip_code": "6320"
    },
    {
      "pk": 825,
      "franchise": 2,
      "name": "OMV LUCIJA VZHOD",
      "address": "Vinjole 29b",
      "lat": 45.50069,
      "lng": 13.61044,
      "prices": {
        "95": 1.354,
        "dizel": 1.683,
        "98": null,
        "100": 1.695,
        "dizel-premium": null,
        "avtoplin-lpg": null,
        "KOEL": null
      },
      "distance": null,
      "direction": "",
      "open_hours": "Okt-Maj: Pon-Ned 06:00-22:00; Jun-Sep: Pon-Čet 06:00-22:00, Pet-Ned 06:00-24:00",
      "zip_code": "6320"
    },
    {
      "pk": 826,
      "franchise": 2,
      "name": "OMV LUCIJA ZAHOD",
      "address": "Seča 188",
      "lat": 45.50043,
      "lng": 13.61022,
      "prices": {
        "95": 1.354,
        "dizel": 1.683,
        "98": null,
        "100": 1.695,
        "dizel-premium": null,
        "avtoplin-lpg": null,
        "KOEL": 1.366
      },
      "distance": null,
      "direction": "",
      "open_hours": "Pon-Ned 06:00-22:00",
      "zip_code": "6320"
    },
    {
      "pk": 829,
      "franchise": 2,
      "name": "OMV MARIBOR BOHOVA",
      "address": "Tržaška c. 83",
      "lat": 46.51809,
      "lng": 15.65131,
      "prices": {
        "95": 1.354,
        "dizel": 1.683,
        "98": null,
        "100": 1.695,
        "dizel-premium": 1.887,
        "avtoplin-lpg": null,
        "KOEL": 1.366
      },
      "distance": null,
      "direction": "",
      "open_hours": "Pon-Ned 06:00-22:00",
      "zip_code": "2000"
    },
    {
      "pk": 830,
      "franchise": 2,
      "name": "OMV MARIBOR PTUJSKA VZHOD",
      "address": "Ptujska cesta 225",
      "lat": 46.522349,
      "lng": 15.679883,
      "prices": {
        "95": 1.354,
        "dizel": 1.683,
        "98": null,
        "100": 1.695,
        "dizel-premium": 1.887,
        "avtoplin-lpg": null,
        "KOEL": null
      },
      "distance": null,
      "direction": "",
      "open_hours": "Pon-Sob 06:00-22:00, Ned/Praz 07:00-21:00",
      "zip_code": "2000"
    },
    {
      "pk": 831,
      "franchise": 2,
      "name": "OMV MARIBOR PTUJSKA ZAHOD",
      "address": "Ptujska cesta 104",
      "lat": 46.53485,
      "lng": 15.66165,
      "prices": {
        "95": 1.354,
        "dizel": 1.683,
        "98": null,
        "100": 1.695,
        "dizel-premium": 1.887,
        "avtoplin-lpg": null,
        "KOEL": 1.366
      },
      "distance": null,
      "direction": "",
      "open_hours": "Pon-Ned 05:00-22:00 (S,N,praz 6-22)",
      "zip_code": "2000"
    },
    {
      "pk": 832,
      "franchise": 2,
      "name": "OMV MARINA KOPER",
      "address": "Kopališko nabrežje 5",
      "lat": 45.55049,
      "lng": 13.72786,
      "prices": {
        "95": 1.354,
        "dizel": 1.683,
        "98": null,
        "100": null,
        "dizel-premium": null,
        "avtoplin-lpg": null,
        "KOEL": null
      },
      "distance": null,
      "direction": "Koper",
      "open_hours": "Okt-Maj: Pon-Sob 08:00-16:00, Ned/Praz 09:00-12:00 in 15:00-20:00; Apr-Sep: Pon-Sob 08:00-20:00, Ned/Praz 09:00-12:00 in 15:00-20:00",
      "zip_code": "6000"
    },
    {
      "pk": 833,
      "franchise": 2,
      "name": "OMV MURSKA SOBOTA",
      "address": "Lendavska 60d",
      "lat": 46.66673,
      "lng": 16.17698,
      "prices": {
        "95": 1.354,
        "dizel": 1.683,
        "98": null,
        "100": 1.695,
        "dizel-premium": 1.887,
        "avtoplin-lpg": null,
        "KOEL": null
      },
      "distance": null,
      "direction": "",
      "open_hours": "Pon-Sob 06:00-22:00",
      "zip_code": "9000"
    },
    {
      "pk": 834,
      "franchise": 2,
      "name": "OMV NOVA VAS",
      "address": "Nova vas 1a",
      "lat": 45.773401,
      "lng": 14.504678,
      "prices": {
        "95": 1.354,
        "dizel": 1.683,
        "98": null,
        "100": 1.695,
        "dizel-premium": null,
        "avtoplin-lpg": null,
        "KOEL": 1.366
      },
      "distance": null,
      "direction": "",
      "open_hours": "Okt-Mar: Pon-Sob 07:00-19:00, Ned/Praz. zaprto; Apr-Sep: Pon-Sob 07:00-20:00, Ned/Praz. zaprto",
      "zip_code": "1385"
    },
    {
      "pk": 835,
      "franchise": 2,
      "name": "OMV NOVO MESTO",
      "address": "Levičnikova c. 4",
      "lat": 45.804054,
      "lng": 15.181842,
      "prices": {
        "95": 1.354,
        "dizel": 1.683,
        "98": null,
        "100": 1.695,
        "dizel-premium": 1.887,
        "avtoplin-lpg": null,
        "KOEL": 1.366
      },
      "distance": null,
      "direction": "",
      "open_hours": "Pon-Ned 06:00-23:00 (S,N,praz 6-22)",
      "zip_code": "8000"
    }
  ],
  "position": null
}
