{
  "count": 553,
  "next": "https://goriva.si/api/v1/search/?format=json&franchise=&name=&o=&page=2&position=&radius=",
  "previous": null,
  "results": [
    {
      "pk": 1574,
      "franchise": 4,
      "name": "BS MOL KOČEVJE 2",
      "address": "REŠKA CESTA 25/A",
      "lat": 45.632833,
      "lng": 14.864267,
      "prices": {
        "95": 1.411,
        "dizel": 1.457,
        "98": null,
        "100": 1.657,
        "dizel-premium": 1.744,
        "avtoplin-lpg": null,
        "KOEL": null
      },
      "distance": null,
      "direction": "",
      "open_hours": "PON - SOB 06:00 - 21:00\r\nNEDELJA IN PRAZNIKI 08:00 - 20:00",
      "zip_code": "1330"
    },
    {
      "pk": 1586,
      "franchise": 4,
      "name": "BS MOL TRBOVLJE",
      "address": "VODENSKA CESTA 28A",
      "lat": 46.142862,
      "lng": 15.036079,
      "prices": {
        "95": 1.411,
        "dizel": 1.457,
        "98": null,
        "100": 1.657,
        "dizel-premium": 1.744,
        "avtoplin-lpg": null,
        "KOEL": null
      },
      "distance": null,
      "direction": "",
      "open_hours": "",
      "zip_code": ""
    },
    {
      "pk": 2056,
      "franchise": 1,
      "name": "PETROL LJUBLJANA - DUNAJSKA 70",
      "address": "DUNAJSKA CESTA 70",
      "lat": 46.06882986,
      "lng": 14.51074492,
      "prices": {
        "95": 1.411,
        "dizel": 1.457,
        "98": null,
        "100": 1.657,
        "dizel-premium": null,
        "avtoplin-lpg": null,
        "KOEL": null
      },
      "distance": null,
      "direction": "",
      "open_hours": "vsak delavnik 06:00-22:00\r\nsobote 07:00-21:00\r\nnedelje in prazniki 07:00-21:00",
      "zip_code": "1000"
    },
    {
      "pk": 2296,
      "franchise": 15,
      "name": "DISCONT OiL - BS Maribor",
      "address": "Tržaška cesta 35",
      "lat": 46.529195,
      "lng": 15.646512,
      "prices": {
        "95": 1.443,
        "dizel": 1.478,
        "98": null,
        "100": 1.679,
        "dizel-premium": null,
        "avtoplin-lpg": 0.769,
        "KOEL": null
      },
      "distance": null,
      "direction": "",
      "open_hours": "Odpiralni čas:\r\nPonedeljek - petek: 07:00 - 20:00\r\nSobota: 07:00 - 19:00\r\nNedelja in prazniki: 08:00 - 13:00",
      "zip_code": "2000"
    },
    {
      "pk": 2327,
      "franchise": 15,
      "name": "DISCONT OiL - BS Bezena",
      "address": "Bezena 99",
      "lat": 46.5499175582367,
      "lng": 15.538353293954877,
      "prices": {
        "95": 1.444,
        "dizel": 1.497,
        "98": null,
        "100": 1.711,
        "dizel-premium": null,
        "avtoplin-lpg": null,
        "KOEL": null
      },
      "distance": null,
      "direction": "",
      "open_hours": "Odpiralni čas: PONEDELJEK - NEDELJA: 06:00 - 22:00",
      "zip_code": "2342"
    },
    {
      "pk": 821,
      "franchise": 2,
      "name": "BS MOL LJUTOMER",
      "address": "Kolodvorska 7a",
      "lat": 46.5289,
      "lng": 16.19006,
      "prices": {
        "95": 1.445,
        "dizel": 1.498,
        "98": null,
        "100": 1.713,
        "dizel-premium": null,
        "avtoplin-lpg": null,
        "KOEL": 1.159
      },
      "distance": null,
      "direction": "",
      "open_hours": "Pon-Ned 06:00-22:00",
      "zip_code": "9240"
    },
    {
      "pk": 2267,
      "franchise": 6,
      "name": "EKO-NAFTA d.o.o.",
      "address": "Trimlini 65A, 9220 Lendava - Lendva",
      "lat": 46.5429019,
      "lng": 16.4429144,
      "prices": {
        "95": 1.445,
        "dizel": 1.498,
        "98": null,
        "100": 1.713,
        "dizel-premium": null,
        "avtoplin-lpg": null,
        "KOEL": 1.159
      },
      "distance": null,
      "direction": "",
      "open_hours": "Ponedeljek-petek\r\n6:00-17:00\r\n\r\nSobota, nedelja, prazniki\r\nZaprto",
      "zip_code": "9220"
    },
    {
      "pk": 2268,
      "franchise": 9,
      "name": "BS Pesniška vrata",
      "address": "Pesnica pri Mariboru 32e",
      "lat": 46.601243,
      "lng": 15.674333,
      "prices": {
        "95": 1.445,
        "dizel": 1.498,
        "98": 1.713,
        "100": 1.713,
        "dizel-premium": null,
        "avtoplin-lpg": null,
        "KOEL": 1.159
      },
      "distance": null,
      "direction": "",
      "open_hours": "ponedeljek - petek: 6-22\r\nsobota: 7-22\r\nnedelja in praznik: 8-20",
      "zip_code": "2211"
    },
    {
      "pk": 2297,
      "franchise": 16,
      "name": "Agas Maribor",
      "address": "Perhavčeva ulica 15",
      "lat": 46.525107,
      "lng": 15.667885,
      "prices": {
        "95": 1.445,
        "dizel": 1.498,
        "98": null,
        "100": null,
        "dizel-premium": null,
        "avtoplin-lpg": 0.769,
        "KOEL": 1.159
      },
      "distance": null,
      "direction": "Maribor Center",
      "open_hours": "Pon do Pet 7:00 - 20:00\r\nSob             8:00 - 13:00",
      "zip_code": "2000"
    },
    {
      "pk": 2299,
      "franchise": 16,
      "name": "Agas Slovenska Bistrica",
      "address": "Žolgarjeva ulica 25",
      "lat": 46.385204,
      "lng": 15.576529,
      "prices": {
        "95": 1.445,
        "dizel": 1.498,
        "98": null,
        "100": null,
        "dizel-premium": null,
        "avtoplin-lpg": 0.769,
        "KOEL": 1.159
      },
      "distance": null,
      "direction": "Izvoz Slovenska Bistrica jug",
      "open_hours": "Pon do Pet 7:00 - 20:00\r\nSob             8:00 - 13:00",
      "zip_code": "2310"
    },
    {
      "pk": 2313,
      "franchise": 14,
      "name": "West Oil BS Zavrč",
      "address": "Zavrč 8c",
      "lat": 46.3896077,
      "lng": 16.05135585,
      "prices": {
        "95": 1.445,
        "dizel": 1.498,
        "98": null,
        "100": null,
        "dizel-premium": null,
        "avtoplin-lpg": null,
        "KOEL": 1.159
      },
      "distance": null,
      "direction": "PTUJ",
      "open_hours": "PON. - PET. 8.00 -18.00\r\nSOB. 8.00 -1600\r\nNEDELJE IN PRAZNIKI - ZAPRTO",
      "zip_code": "2283"
    },
    {
      "pk": 2315,
      "franchise": 21,
      "name": "Bencinski servis STRANICE",
      "address": "Osredek 33",
      "lat": 46.36054099833075,
      "lng": 15.385325730057207,
      "prices": {
        "95": 1.445,
        "dizel": 1.498,
        "98": null,
        "100": null,
        "dizel-premium": null,
        "avtoplin-lpg": null,
        "KOEL": 1.159
      },
      "distance": null,
      "direction": "",
      "open_hours": "ponedeljek-sobota  6-22 ure\r\nnedelja in prazniki   7-22 ure",
      "zip_code": "3214"
    },
    {
      "pk": 766,
      "franchise": 2,
      "name": "BS MOL AJŠEVICA",
      "address": "Loke 40",
      "lat": 45.95337,
      "lng": 13.69157,
      "prices": {
        "95": 1.491,
        "dizel": 1.523,
        "98": null,
        "100": 1.761,
        "dizel-premium": null,
        "avtoplin-lpg": null,
        "KOEL": null
      },
      "distance": null,
      "direction": "",
      "open_hours": "Ned-Čet 06:00-22:00; Pet-Sob 06:00-24:00",
      "zip_code": "5000"
    },
    {
      "pk": 769,
      "franchise": 2,
      "name": "BS MOL BRESTOVICA",
      "address": "Brestovica 116b",
      "lat": 45.81302,
      "lng": 13.62228,
      "prices": {
        "95": 1.491,
        "dizel": 1.523,
        "98": null,
        "100": null,
        "dizel-premium": null,
        "avtoplin-lpg": null,
        "KOEL": null
      },
      "distance": null,
      "direction": "",
      "open_hours": "Okt-Mar: Pon-Ned 07:00-19:00; Apr-Sep: Pon-Ned 07:00-20:00",
      "zip_code": "6223"
    },
    {
      "pk": 771,
      "franchise": 2,
      "name": "BS MOL BREŽICE",
      "address": "C.Svobode 35",
      "lat": 45.913737,
      "lng": 15.595365,
      "prices": {
        "95": 1.491,
        "dizel": 1.523,
        "98": null,
        "100": 1.761,
        "dizel-premium": 1.795,
        "avtoplin-lpg": null,
        "KOEL": 1.17
      },
      "distance": null,
      "direction": "",
      "open_hours": "Pon-Ned 06:00-22:00",
      "zip_code": "8250"
    },
    {
      "pk": 773,
      "franchise": 4,
      "name": "BS MOL CELJE MARIBORSKA JUG",
      "address": "Mariborska c. 84",
      "lat": 46.23923,
      "lng": 15.27456,
      "prices": {
        "95": 1.491,
        "dizel": 1.523,
        "98": null,
        "100": 1.761,
        "dizel-premium": 1.795,
        "avtoplin-lpg": null,
        "KOEL": 1.17
      },
      "distance": null,
      "direction": "",
      "open_hours": "Sep-Maj: Pon-Ned 05:00-22:00; Jun-Avg: Pon-Ned 05:00-23:00",
      "zip_code": "3000"
    },
    {
      "pk": 774,
      "franchise": 2,
      "name": "BS MOL CELJE LJUBLJANSKA",
      "address": "Ljubljanska cesta 110",
      "lat": 46.238118,
      "lng": 15.235194,
      "prices": {
        "95": 1.491,
        "dizel": 1.523,
        "98": null,
        "100": 1.761,
        "dizel-premium": null,
        "avtoplin-lpg": null,
        "KOEL": null
      },
      "distance": null,
      "direction": "",
      "open_hours": "Pon-Pet 05:00-22:00, Sob/Ned/Praz 06:00-21:00",
      "zip_code": "3000"
    },
    {
      "pk": 775,
      "franchise": 2,
      "name": "BS MOL ČRNOMELJ",
      "address": "Belokranjska c. 18a",
      "lat": 45.57995,
      "lng": 15.19583,
      "prices": {
        "95": 1.491,
        "dizel": 1.523,
        "98": null,
        "100": 1.761,
        "dizel-premium": 1.795,
        "avtoplin-lpg": null,
        "KOEL": null
      },
      "distance": null,
      "direction": "",
      "open_hours": "Pon-Ned 06:00-22:00",
      "zip_code": "8340"
    },
    {
      "pk": 776,
      "franchise": 2,
      "name": "BS MOL DIVAČA",
      "address": "Kolodvorska 1",
      "lat": 45.681494,
      "lng": 13.968687,
      "prices": {
        "95": 1.491,
        "dizel": 1.523,
        "98": null,
        "100": 1.761,
        "dizel-premium": null,
        "avtoplin-lpg": null,
        "KOEL": 1.17
      },
      "distance": null,
      "direction": "",
      "open_hours": "Okt-Maj: Pon-Sob 06:00-20:00, Ned/Praz. zaprto; Jun-Sep: Pon-Sob 06:00-21:00, Ned/Praz. 9-18",
      "zip_code": "6215"
    },
    {
      "pk": 779,
      "franchise": 2,
      "name": "BS MOL DOL PRI LJUBLJANI",
      "address": "Podgora pri Dolskem 40",
      "lat": 46.090168,
      "lng": 14.650805,
      "prices": {
        "95": 1.491,
        "dizel": 1.523,
        "98": null,
        "100": 1.761,
        "dizel-premium": null,
        "avtoplin-lpg": null,
        "KOEL": 1.17
      },
      "distance": null,
      "direction": "",
      "open_hours": "Pon-Ned 05:00-22:00",
      "zip_code": "1262"
    },
    {
      "pk": 780,
      "franchise": 2,
      "name": "BS MOL DRAVOGRAD",
      "address": "Koroška c. 49",
      "lat": 46.59033,
      "lng": 15.01542,
      "prices": {
        "95": 1.491,
        "dizel": 1.523,
        "98": null,
        "100": 1.761,
        "dizel-premium": null,
        "avtoplin-lpg": null,
        "KOEL": 1.17
      },
      "distance": null,
      "direction": "",
      "open_hours": "Okt-Maj: Pon-Ned 06:00-20:00; Jun-Sep: Pon-Sob 06:00-21:00, Ned/Praz 07:00-20:00",
      "zip_code": "2370"
    },
    {
      "pk": 783,
      "franchise": 2,
      "name": "BS MOL DUTOVLJE",
      "address": "Dutovlje 3b",
      "lat": 45.755992,
      "lng": 13.835896,
      "prices": {
        "95": 1.491,
        "dizel": 1.523,
        "98": null,
        "100": 1.761,
        "dizel-premium": null,
        "avtoplin-lpg": null,
        "KOEL": 1.17
      },
      "distance": null,
      "direction": "",
      "open_hours": "Okt-Mar: Pon-Ned 07:00-20:00; Apr-Sep: Pon-Ned 07:00-21:00",
      "zip_code": "6221"
    },
    {
      "pk": 789,
      "franchise": 2,
      "name": "BS MOL FERNETIČI",
      "address": "Partizanska c. 151",
      "lat": 45.701768,
      "lng": 13.841505,
      "prices": {
        "95": 1.491,
        "dizel": 1.523,
        "98": null,
        "100": 1.761,
        "dizel-premium": 1.795,
        "avtoplin-lpg": 0.818,
        "KOEL": null
      },
      "distance": null,
      "direction": "Sežana",
      "open_hours": "Pon-Ned 07:00-22:00",
      "zip_code": "6210"
    },
    {
      "pk": 792,
      "franchise": 2,
      "name": "BS MOL GEDEROVCI",
      "address": "Gederovci 17a",
      "lat": 46.67921,
      "lng": 16.056079,
      "prices": {
        "95": 1.491,
        "dizel": 1.523,
        "98": null,
        "100": 1.761,
        "dizel-premium": null,
        "avtoplin-lpg": null,
        "KOEL": 1.17
      },
      "distance": null,
      "direction": "",
      "open_hours": "Pon-Pet 5:00-22:00; Sob 6:00-22:00;Ned/Praz 7:00-21:00",
      "zip_code": "9251"
    },
    {
      "pk": 794,
      "franchise": 2,
      "name": "BS MOL GRAČIŠČE",
      "address": "Gračišče 4a",
      "lat": 45.501301,
      "lng": 13.873635,
      "prices": {
        "95": 1.491,
        "dizel": 1.523,
        "98": null,
        "100": null,
        "dizel-premium": null,
        "avtoplin-lpg": null,
        "KOEL": null
      },
      "distance": null,
      "direction": "",
      "open_hours": "Okt-Mar: Pon-Sob 07:00-19:00, Ned/Praz 08:00-19:00; Apr-Maj: Pon-Ned 07:00-20:00; Jun-Sep: Pon-Ned 07:00-21:00",
      "zip_code": "6272"
    }
  ],
  "position": null
}
